setup.py
django_comments/__init__.py
django_comments/defaults.py
django_comments/exceptions.py
django_comments/models.py
django_comments/plugins.py
django_comments/settings.py
django_comments/signals.py
django_comments/urls.py
django_comments/views.py
django_comments.egg-info/PKG-INFO
django_comments.egg-info/SOURCES.txt
django_comments.egg-info/dependency_links.txt
django_comments.egg-info/top_level.txt
django_comments/tests/__init__.py
django_comments/tests/plugin_pool.py