Metadata-Version: 1.1
Name: django-comments
Version: 1.0.0.b
Summary: Generic pluggable comments application
Home-page: http://pypi.python.org/pypi/django-comments
Author: marazmiki
Author-email: marazmiki@gmail.com
License: MIT license
Download-URL: http://bitbucket.org/marazmiki/django-comments/get/tip.zip
Platform: UNKNOWN
Classifier: Development Status :: 4 - Beta
Classifier: Framework :: Django
Classifier: Intended Audience :: Developers
Classifier: License :: OSI Approved :: MIT License
Classifier: Programming Language :: Python
Classifier: Topic :: Software Development :: Libraries :: Python Modules
Requires: django (>=1.3)
